[{"stationuuid": "196a749d-d9ce-4961-ba74-d9e416103ee5", "name": "Radio Maria Ivory Coast", "url_resolved": "https://dreamsiteradiocp6.com/proxy/rmcosta?mp=/stream", "favicon": "https://www.radiomaria.ci/wp-content/uploads/2016/09/per-itunes.jpg"}, {"stationuuid": "739f485a-e8a2-4fcc-9fad-65ab509125cf", "name": "Life radio Côte d’Ivoire", "url_resolved": "https://cast4.asurahosting.com/proxy/life/stream", "favicon": ""}, {"stationuuid": "0d7c9963-2239-4384-8061-d2da2516bb68", "name": "Africa Radio Abidjan", "url_resolved": "https://africaradio.ice.infomaniak.ch/abidjan128.mp3", "favicon": ""}, {"stationuuid": "1a29a057-1127-4906-b93e-dd2a7bdb57bf", "name": "Afrobeat international", "url_resolved": "https://listen.radioking.com/radio/397789/stream/449770", "favicon": ""}, {"stationuuid": "f7a86f1f-df67-4e66-b5b4-f562a0efb9fd", "name": "Skyrock Abidjan", "url_resolved": "https://icecast.skyrock.net/s/abidjan_aac_64k", "favicon": ""}, {"stationuuid": "5529f18f-c425-452d-901b-0ba5eae89335", "name": "Radio Jam", "url_resolved": "https://listen.radioking.com/radio/61201/stream/98566", "favicon": ""}, {"stationuuid": "a86a21cd-0940-47ae-a9f6-ac37a4f16e07", "name": "Abdulbasit Abdulsamad", "url_resolved": "https://radio.mp3islam.com/listen/abdulbasit/radio.mp3", "favicon": "null"}]