[{"stationuuid": "97887f52-540f-409e-a625-967e4698d829", "name": "Falklands Radio 530 Stanley", "url_resolved": "https://streaming.broadcastradio.com:8332/flklnd", "favicon": ""}, {"stationuuid": "c7571d24-b6b2-43f4-b9ba-2e42a1cbc45e", "name": "Falklands Radio", "url_resolved": "https://streaming.broadcastradio.com:8332/flklnd?1721893143541=", "favicon": "https://api.broadcast.radio/api/image/464937d5-67d8-42e7-886c-426239fa26dd.png?g=center"}, {"stationuuid": "873e8220-51cd-43ca-96bd-6dcd09ecc884", "name": "BFBS Falklands", "url_resolved": "https://listen-ssvcbfbs.sharp-stream.com/ssvcbfbs6.aac", "favicon": "https://media.info/l/o/5/5.1647094643.png"}, {"stationuuid": "6cad9579-17eb-45a4-a885-562a28824029", "name": "Abdulbasit Abdulsamad", "url_resolved": "https://radio.mp3islam.com/listen/abdulbasit/radio.mp3", "favicon": "null"}]