[{"stationuuid": "bc1e8eb3-a94e-48d7-892a-e790a1599b60", "name": "SumerFm Iraq", "url_resolved": "https://l3.itworkscdn.net/itwaudio/9012/stream", "favicon": ""}, {"stationuuid": "84e746a9-e2d3-42ff-b09f-e788660fdf28", "name": ". Al quran radio", "url_resolved": "https://n0a.radiojar.com/0tpy1h0kxtzuv?rj-ttl=5&rj-tok=AAABhdgGORQA-2acfyF3_4WY2g", "favicon": ""}, {"stationuuid": "2d7d377c-5146-4784-9014-b01f17069bde", "name": ".. مختصر التفسير", "url_resolved": "https://qurango.net/radio/mukhtasartafsir", "favicon": ""}, {"stationuuid": "d3434153-afc3-4bdc-a98b-51ddca3990f1", "name": ". القارئ محمد أيوب", "url_resolved": "https://qurango.net/radio/mohammed_ayyub", "favicon": ""}, {"stationuuid": "a29b614a-6dd1-4e98-a7f7-a70eb21f82fb", "name": "Al-bilad Radio/Yaqoubi", "url_resolved": "https://streamer.radio.co/sb38bf6e66/listen", "favicon": "https://images.radio.co/station_logos/sb38bf6e66.20180614123831.jpg"}, {"stationuuid": "98e58b0a-e3e0-4833-b585-418c7cd7e204", "name": "Rudaw News Radio", "url_resolved": "https://l3.itworkscdn.net/itwaudio/9006/stream", "favicon": "https://commons.wikimedia.org/wiki/File:Rudaw_Media_Network.jpg"}, {"stationuuid": "f236ce08-8acd-4190-8133-799e5ab02afe", "name": "Waar Radio Official Stream", "url_resolved": "https://c2.radioboss.fm:18564/stream", "favicon": "https://upload.wikimedia.org/wikipedia/commons/d/d2/WAAR_TV_HD.png"}, {"stationuuid": "894f73d0-647d-461b-845c-95d8e14a1e32", "name": "Alseraj Radio Islam", "url_resolved": "https://eu4.fastcast4u.com/proxy/aabdul00?mp=/1", "favicon": ""}, {"stationuuid": "448ba0a5-0c40-4f53-adc6-9d7f8b6e5f6a", "name": "Darusalam Radio", "url_resolved": "https://streams.radio.co/s0975ec186/listen", "favicon": "https://images.radio.co/station_logos/s0975ec186.20220716110749.jpg"}, {"stationuuid": "abf148ba-cb50-4d30-a0da-ee68620019aa", "name": "Kurdistan 24", "url_resolved": "https://audio-edge-3mayu.fra.h.radiomast.io/04b1ce4c-24f2-4172-b756-065832ef78bf", "favicon": ""}, {"stationuuid": "79e3bcb9-a030-4832-870e-0933f3bde362", "name": "Radio Shanasheel", "url_resolved": "https://stream-152.zeno.fm/a33ka0d94p8uv", "favicon": ""}, {"stationuuid": "0cb24613-f3ba-41d6-9410-b3aaaa49c3f9", "name": "Al rasheed fm", "url_resolved": "https://streaming.shoutcast.com/alrasheed-fm?1719771692024", "favicon": ""}, {"stationuuid": "78fe4c57-8bfd-481b-a368-292581e4f6f5", "name": "Turkmen FM  تركمان إف إم", "url_resolved": "https://radyo1.radyo-dinle.tc/8284/stream;", "favicon": "null"}, {"stationuuid": "27db183f-6aaa-421d-885f-786b172c5b9c", "name": "Radio Shanasheel", "url_resolved": "https://stream-152.zeno.fm/a33ka0d94p8uv", "favicon": ""}, {"stationuuid": "cd5a924a-29a6-4114-84ef-8effa816cfa7", "name": "FM المستقبل", "url_resolved": "https://edge.mixlr.com/channel/vnvcj", "favicon": "null"}, {"stationuuid": "b8ab13a0-938d-4600-92bc-44d2a85b13ae", "name": "Radio Duhok FM", "url_resolved": "https://stream-149.zeno.fm/unwq3jdyhmbuv", "favicon": ""}, {"stationuuid": "fa5ae1db-2562-433b-9bcb-10a4165b5a89", "name": "Shafaq radio", "url_resolved": "https://radio.shafaq.com/radio", "favicon": ""}, {"stationuuid": "d6d9ace0-eb06-4a81-890b-3c24550003d5", "name": "Radyo  Şirvan Perwer", "url_resolved": "https://stream-156.zeno.fm/x0xhw6c6g2zuv?zs=AfL9IRdsQ_qHIebZBo-9GA", "favicon": "null"}, {"stationuuid": "d41734a8-bf16-479a-904d-d97163ef509a", "name": "Abdulbasit Abdulsamad", "url_resolved": "https://radio.mp3islam.com/listen/abdulbasit/radio.mp3", "favicon": "null"}, {"stationuuid": "82dfb2fd-4c20-4cf3-b023-26e32ae38b55", "name": "Waar radio", "url_resolved": "https://c2.radioboss.fm/stream/564", "favicon": ""}, {"stationuuid": "93a0d452-a064-4ddb-b0f2-eec75693acfb", "name": "Radio Ashur  راديو أشور ܦܪܵܣ ܩܵܠܵܐ ܕܐܵܫܘܿܪ", "url_resolved": "https://eu7.fastcast4u.com/proxy/radioashur?mp=/1", "favicon": "https://zowaa.org/ashur-radio/"}]